scraps/ESL_tools.py
scraps/__init__.py
scraps/plot_tools.py
scraps/process_file.py
scraps/resonator.py
scraps/resonator_sweep.py
scraps/fitsS21/__init__.py
scraps/fitsS21/baselines.py
scraps/fitsS21/cmplxIQ.py
scraps/fitsS21/hanger_resonator.py
scraps/fitsS21/inline_ground_terminated_resonator_s11.py
scraps/fitsS21/inline_resonator.py
scraps/fitsS21/utils.py
scraps/fitsSweep/__init__.py
scraps/fitsSweep/tls_mbt_barmat.py
scraps/fitsSweep/tls_mbt_basic.py
scraps-0.5.3.dist-info/LICENSE.txt
scraps-0.5.3.dist-info/METADATA
scraps-0.5.3.dist-info/WHEEL
scraps-0.5.3.dist-info/top_level.txt
scraps-0.5.3.dist-info/RECORD
