Metadata-Version: 2.1
Name: scraps
Version: 0.5.3
Summary: SuperConducting Resonator Analysis and Plotting Software.
Home-page: http://github.com/FaustinCarter/scraps
Author: Faustin Carter
Author-email: faustin.carter@gmail.com
License: MIT
Classifier: Development Status :: 4 - Beta
Classifier: Intended Audience :: Science/Research
Classifier: License :: OSI Approved :: MIT License
Classifier: Programming Language :: Python
Classifier: Topic :: Scientific/Engineering :: Visualization
License-File: LICENSE.txt
Requires-Dist: numpy >=1.5
Requires-Dist: matplotlib >=2.0
Requires-Dist: scipy >=0.14
Requires-Dist: lmfit >=0.9.5
Requires-Dist: emcee >=2.2.1
Requires-Dist: pandas >=0.18
